{
  "LastUpdate": "26-04-04-21-30",
  "Version": "1.1.0.0",
  "Build": "1100",
  "StationBuild": "2",
  "TrainBuild": "3",
  "github": "https://gh-proxy.com/https://github.com/CrYinLang/EmuTrain/releases/download/1.1.0.0/app-release.apk",
  "gitee": "https://gitee.com/CrYinLang/EmuTrain/releases/download/1.1.0.0/app-release.apk",
  "qq": "https://qm.qq.com/q/fk5M9PJGyk",
  "describe": "更新了很多东西\n1.GPS速度仪上线,可以看速度和路径,(还不能保存)\n2.新增大量CR200J数据库,修复不能看动集\n3.优化部分图标和修改\n4.新增车型查询功能,可以看该车型所有车\n速速更新",
  "Announcement": "公告:QQ群:667933194\n官网:https://emutrain.github.io/"
}
